reference_api_buddy/__init__.py
reference_api_buddy/cli.py
reference_api_buddy/cache/__init__.py
reference_api_buddy/cache/engine.py
reference_api_buddy/core/__init__.py
reference_api_buddy/core/admin_utils.py
reference_api_buddy/core/config.py
reference_api_buddy/core/handler.py
reference_api_buddy/core/inflight_tracker.py
reference_api_buddy/core/proxy.py
reference_api_buddy/core/server.py
reference_api_buddy/core/ttl_manager.py
reference_api_buddy/database/__init__.py
reference_api_buddy/database/manager.py
reference_api_buddy/database/models.py
reference_api_buddy/monitoring/manager.py
reference_api_buddy/security/__init__.py
reference_api_buddy/security/manager.py
reference_api_buddy/throttling/__init__.py
reference_api_buddy/throttling/manager.py
reference_api_buddy/utils/__init__.py
reference_api_buddy/utils/logger.py
reference_api_buddy-0.5.0.dist-info/licenses/LICENSE
reference_api_buddy-0.5.0.dist-info/METADATA
reference_api_buddy-0.5.0.dist-info/WHEEL
reference_api_buddy-0.5.0.dist-info/entry_points.txt
reference_api_buddy-0.5.0.dist-info/top_level.txt
reference_api_buddy-0.5.0.dist-info/RECORD
