Metadata-Version: 2.4
Name: reference-api-buddy
Version: 0.5.0
Summary: HTTP caching proxy module for development environments with reference APIs
Author-email: Reference API Buddy Team <tinkermonkey25@gmail.com>
Maintainer-email: Reference API Buddy Team <tinkermonkey25@gmail.com>
License: MIT License
Project-URL: Homepage, https://github.com/tinkermonkey/reference-api-buddy
Project-URL: Repository, https://github.com/tinkermonkey/reference-api-buddy
Project-URL: Issues, https://github.com/tinkermonkey/reference-api-buddy/issues
Project-URL: Changelog, https://github.com/tinkermonkey/reference-api-buddy/blob/main/CHANGELOG.md
Keywords: proxy,caching,api,http,development,rate-limiting
Classifier: Development Status :: 4 - Beta
Classifier: Intended Audience :: Developers
Classifier: License :: OSI Approved :: MIT License
Classifier: Programming Language :: Python :: 3
Classifier: Programming Language :: Python :: 3.8
Classifier: Programming Language :: Python :: 3.9
Classifier: Programming Language :: Python :: 3.10
Classifier: Programming Language :: Python :: 3.11
Classifier: Programming Language :: Python :: 3.12
Classifier: Programming Language :: Python :: 3.13
Classifier: Topic :: Internet :: Proxy Servers
Classifier: Topic :: Software Development :: Libraries :: Python Modules
Classifier: Topic :: System :: Networking
Requires-Python: >=3.8
License-File: LICENSE
Requires-Dist: requests>=2.32.0
Requires-Dist: urllib3>=2.5.0
Requires-Dist: certifi>=2025.8.0
Requires-Dist: charset-normalizer>=3.4.0
Requires-Dist: idna>=3.10
Provides-Extra: dev
Requires-Dist: pytest>=7.0; extra == "dev"
Requires-Dist: pytest-cov>=4.0; extra == "dev"
Requires-Dist: pytest-timeout>=2.1; extra == "dev"
Requires-Dist: black>=23.0; extra == "dev"
Requires-Dist: isort>=5.12; extra == "dev"
Requires-Dist: flake8>=6.0; extra == "dev"
Requires-Dist: mypy>=1.0; extra == "dev"
Requires-Dist: pre-commit>=3.0; extra == "dev"
Requires-Dist: autopep8>=2.3.0; extra == "dev"
Requires-Dist: build>=1.3.0; extra == "dev"
Requires-Dist: coverage>=7.10.0; extra == "dev"
Requires-Dist: twine>=6.1.0; extra == "dev"
Requires-Dist: typing-extensions>=4.14.0; extra == "dev"
Requires-Dist: pip-audit>=2.9.0; extra == "dev"
Provides-Extra: docs
Requires-Dist: sphinx>=6.0; extra == "docs"
Requires-Dist: sphinx-rtd-theme>=1.3; extra == "docs"
Requires-Dist: myst-parser>=2.0; extra == "docs"
Dynamic: license-file
